omim/__init__.py
omim/bin/__init__.py
omim/bin/_faq.py
omim/bin/_query.py
omim/bin/_stats.py
omim/bin/_update.py
omim/bin/cli.py
omim/core/__init__.py
omim/core/entry.py
omim/core/other.py
omim/core/update.py
omim/data/omim.sqlite3
omim/db/__init__.py
omim/db/manager.py
omim/db/model.py
omim/util/__init__.py
omim/version/version.json
omim-1.0.4.dist-info/METADATA
omim-1.0.4.dist-info/WHEEL
omim-1.0.4.dist-info/entry_points.txt
omim-1.0.4.dist-info/top_level.txt
omim-1.0.4.dist-info/RECORD
