Metadata-Version: 2.1
Name: omim
Version: 1.0.4
Summary: OMIM - Online Mendelian Inheritance in Man
Home-page: https://github.com/suqingdong/omim
Author: suqingdong
Author-email: suqingdong1114@gmail.com
License: BSD License
Project-URL: Documentation, https://omim.readthedocs.io
Project-URL: Tracker, https://github.com/suqingdong/omim/issues
Platform: UNKNOWN
Classifier: Development Status :: 5 - Production/Stable
Classifier: Operating System :: OS Independent
Classifier: Intended Audience :: Developers
Classifier: License :: OSI Approved :: MIT License
Classifier: Programming Language :: Python
Classifier: Programming Language :: Python :: 3
Classifier: Programming Language :: Python :: 3.8
Classifier: Topic :: Software Development :: Libraries
Requires-Dist: click
Requires-Dist: pygments
Requires-Dist: requests
Requires-Dist: webrequests
Requires-Dist: prettytable
Requires-Dist: simple-loggers
Requires-Dist: python-dateutil
